tigerbeetle/__init__.py
tigerbeetle/bindings.py
tigerbeetle/client.py
tigerbeetle/lib.py
tigerbeetle/py.typed
tigerbeetle/lib/aarch64-linux-gnu.2.27/libtb_client.so
tigerbeetle/lib/aarch64-linux-musl/libtb_client.so
tigerbeetle/lib/aarch64-macos/libtb_client.dylib
tigerbeetle/lib/x86_64-linux-gnu.2.27/libtb_client.so
tigerbeetle/lib/x86_64-linux-musl/libtb_client.so
tigerbeetle/lib/x86_64-macos/libtb_client.dylib
tigerbeetle/lib/x86_64-windows/tb_client.dll
tigerbeetle-0.16.69.dist-info/METADATA
tigerbeetle-0.16.69.dist-info/WHEEL
tigerbeetle-0.16.69.dist-info/RECORD
