Metadata-Version: 2.4
Name: tigerbeetle
Version: 0.16.69
Summary: The TigerBeetle client for Python.
Project-URL: Homepage, https://github.com/tigerbeetle/tigerbeetle
Project-URL: Issues, https://github.com/tigerbeetle/tigerbeetle/issues
Classifier: Development Status :: 5 - Production/Stable
Classifier: License :: OSI Approved :: Apache Software License
Classifier: Operating System :: MacOS :: MacOS X
Classifier: Operating System :: Microsoft :: Windows
Classifier: Operating System :: POSIX :: Linux
Classifier: Programming Language :: Python :: 3
Classifier: Topic :: Database :: Front-Ends
Requires-Python: >=3.7
